rtg_score/__init__.py
rtg_score-0.1.0.dist-info/LICENSE
rtg_score-0.1.0.dist-info/METADATA
rtg_score-0.1.0.dist-info/WHEEL
rtg_score-0.1.0.dist-info/top_level.txt
rtg_score-0.1.0.dist-info/RECORD
