Metadata-Version: 2.1
Name: rtg-score
Version: 0.1.0
Summary: Analysis of confounders by Rank-to-Group scores
Home-page: UNKNOWN
Author: Alex Rogozhnikov, System1 Biosciences
License: UNKNOWN
Keywords: variability analysis,variability decomposition,contributing factors
Platform: UNKNOWN
Classifier: Intended Audience :: Science/Research
Classifier: Programming Language :: Python :: 3 
Requires-Dist: numpy
Requires-Dist: scipy
Requires-Dist: pandas
Requires-Dist: scikit-learn
